quackbox/__init__.py
quackbox/leaderboard.py
quackbox/save_data.py
quackbox-0.1.2.dist-info/METADATA
quackbox-0.1.2.dist-info/WHEEL
quackbox-0.1.2.dist-info/licenses/LICENSE
quackbox-0.1.2.dist-info/RECORD
